AutoIntegrityCheck/validator.cp310-win_amd64.pyd
AutoIntegrityCheck-0.1.dist-info/METADATA
AutoIntegrityCheck-0.1.dist-info/WHEEL
AutoIntegrityCheck-0.1.dist-info/top_level.txt
AutoIntegrityCheck-0.1.dist-info/RECORD
