Metadata-Version: 2.1
Name: AutoIntegrityCheck
Version: 0.1
Summary: A tool to validate the integrity of Automatic1111/SdNext environments
Home-page: http://github.com/d8ahazard/AutoIntegrityCheck
Author: digitalhigh
Author-email: d8ahazard@gmail.com
Classifier: Programming Language :: Python :: 3
Classifier: License :: OSI Approved :: MIT License
Classifier: Operating System :: OS Independent
Requires-Dist: gitpython
Requires-Dist: requests
